aspen_dynamo/__init__.py
aspen_dynamo/benchmark.py
aspen_dynamo-0.1.3.dist-info/licenses/LICENSE
aspen_dynamo-0.1.3.dist-info/METADATA
aspen_dynamo-0.1.3.dist-info/WHEEL
aspen_dynamo-0.1.3.dist-info/top_level.txt
aspen_dynamo-0.1.3.dist-info/RECORD
