Metadata-Version: 2.4
Name: aspen-dynamo
Version: 0.1.3
Summary: Async DynamoDB table helper based on aioboto3.
License-Expression: MIT
Requires-Python: >=3.10
License-File: LICENSE
Requires-Dist: aioboto3
Requires-Dist: pydantic>=2.0
Provides-Extra: dev
Requires-Dist: flake8; extra == "dev"
Requires-Dist: isort; extra == "dev"
Requires-Dist: pytest; extra == "dev"
Requires-Dist: pytest-asyncio; extra == "dev"
Requires-Dist: pytest-cov; extra == "dev"
Requires-Dist: pyright[nodejs]; extra == "dev"
Requires-Dist: types-aioboto3[dynamodb]; extra == "dev"
Provides-Extra: benchmark
Requires-Dist: uvloop; extra == "benchmark"
Requires-Dist: aiodynamo[aiohttp,httpx]; extra == "benchmark"
Dynamic: license-file
